{
    "party": "karama",
    "name": "نضال سعودي",
    "briefDiscrp": "لكن لا بــــد أن أوضح لك أن كل هذه الأفكار لمغلوطــة حول ",
    "thumbImage": "../../data/images/ni4al_head.png",
    "slug": "nedhal-soudi",
    "facebookSlug": "nidhalsaoudi89",
    "viewershipStats": {
        "full": [
            {
                "timestamp": 1620446400,
                "views": 4,
                "duration": 501,
                "viewsSinceStart": 482013
            },
            {
                "timestamp": 1612933200,
                "views": 111000,
                "duration": 1047,
                "viewsSinceStart": 482009
            },
            {
                "timestamp": 1612760400,
                "views": 41000,
                "duration": 740,
                "viewsSinceStart": 371009
            },
            {
                "timestamp": 1607576400,
                "views": 140000,
                "duration": 571,
                "viewsSinceStart": 330009
            },
            {
                "timestamp": 1607490000,
                "views": 38000,
                "duration": 442,
                "viewsSinceStart": 190009
            },
            {
                "timestamp": 1605762000,
                "views": 8000,
                "duration": 552,
                "viewsSinceStart": 152009
            },
            {
                "timestamp": 1605762000,
                "views": 17000,
                "duration": 511,
                "viewsSinceStart": 144009
            },
            {
                "timestamp": 1604811600,
                "views": 10000,
                "duration": 4236,
                "viewsSinceStart": 127009
            },
            {
                "timestamp": 1595995200,
                "views": 4,
                "duration": 65,
                "viewsSinceStart": 117009
            },
            {
                "timestamp": 1594958400,
                "views": 33000,
                "duration": 269,
                "viewsSinceStart": 117005
            },
            {
                "timestamp": 1594353600,
                "views": 84000,
                "duration": 544,
                "viewsSinceStart": 84005
            },
            {
                "timestamp": 1585281600,
                "views": 5,
                "duration": 1251,
                "viewsSinceStart": 5
            }
        ],
        "brief": {
            "viewsPerLive": 40167,
            "aggregateViews": 482013,
            "aggregateDuration": 10729
        }
    }
}
